{
  "gameId": 17,
  "dateString": "2026-07-11",
  "firstLetter": "O",
  "interval": "1d",
  "sector": "Communication Services",
  "marketCapTier": "Large Cap",
  "triviaHints": [
    "TODO: trivia hint 1",
    "TODO: trivia hint 2"
  ],
  "candlestickData": [
    {
      "x": "2013-11-26",
      "y": [
        74.56,
        76.29,
        74.38,
        74.85
      ]
    },
    {
      "x": "2013-11-27",
      "y": [
        73.81,
        74.45,
        73.19,
        74.09
      ]
    },
    {
      "x": "2013-11-28",
      "y": [
        73.16,
        73.69,
        72.51,
        72.71
      ]
    },
    {
      "x": "2013-11-29",
      "y": [
        73.55,
        76.2,
        73.36,
        75.97
      ]
    },
    {
      "x": "2013-11-30",
      "y": [
        75.66,
        75.71,
        73.78,
        75.22
      ]
    },
    {
      "x": "2013-12-01",
      "y": [
        75.31,
        75.34,
        73.29,
        73.74
      ]
    },
    {
      "x": "2013-12-02",
      "y": [
        75.28,
        77.16,
        74.82,
        75.63
      ]
    },
    {
      "x": "2013-12-03",
      "y": [
        76.06,
        76.17,
        75.02,
        75.31
      ]
    },
    {
      "x": "2013-12-04",
      "y": [
        74.76,
        75.64,
        73.95,
        75.07
      ]
    },
    {
      "x": "2013-12-05",
      "y": [
        75.2,
        76.36,
        74.64,
        75.63
      ]
    },
    {
      "x": "2013-12-06",
      "y": [
        74.75,
        75.85,
        73.63,
        73.98
      ]
    },
    {
      "x": "2013-12-07",
      "y": [
        73.98,
        76.17,
        73.31,
        75.59
      ]
    },
    {
      "x": "2013-12-08",
      "y": [
        76.2,
        77.65,
        75.08,
        76.68
      ]
    },
    {
      "x": "2013-12-09",
      "y": [
        76.47,
        77.23,
        75.94,
        76.51
      ]
    },
    {
      "x": "2013-12-10",
      "y": [
        76.85,
        77.39,
        76.25,
        77.37
      ]
    },
    {
      "x": "2013-12-11",
      "y": [
        77.21,
        78.1,
        75.71,
        76.31
      ]
    },
    {
      "x": "2013-12-12",
      "y": [
        75.48,
        75.6,
        70.84,
        71.35
      ]
    },
    {
      "x": "2013-12-13",
      "y": [
        70.3,
        72.74,
        70.29,
        72.55
      ]
    },
    {
      "x": "2013-12-14",
      "y": [
        73.57,
        73.63,
        71.82,
        72.96
      ]
    },
    {
      "x": "2013-12-15",
      "y": [
        72.99,
        74.27,
        72.99,
        73.66
      ]
    },
    {
      "x": "2013-12-16",
      "y": [
        73.25,
        75.2,
        72.82,
        73.43
      ]
    },
    {
      "x": "2013-12-17",
      "y": [
        73.61,
        74.87,
        71.52,
        73.09
      ]
    },
    {
      "x": "2013-12-18",
      "y": [
        74.5,
        75.99,
        73.32,
        73.93
      ]
    },
    {
      "x": "2013-12-19",
      "y": [
        73.43,
        74.03,
        71.85,
        72.83
      ]
    },
    {
      "x": "2013-12-20",
      "y": [
        72.79,
        77.08,
        72.41,
        76.11
      ]
    },
    {
      "x": "2013-12-21",
      "y": [
        76.13,
        78.77,
        75.37,
        78.62
      ]
    },
    {
      "x": "2013-12-22",
      "y": [
        78.75,
        80.24,
        78.45,
        79.9
      ]
    },
    {
      "x": "2013-12-23",
      "y": [
        81.49,
        81.88,
        80.67,
        80.84
      ]
    },
    {
      "x": "2013-12-24",
      "y": [
        80.07,
        80.15,
        77.98,
        78.6
      ]
    },
    {
      "x": "2013-12-25",
      "y": [
        77.96,
        81.47,
        77.12,
        80.83
      ]
    }
  ]
}
